{"frames":{"Idle_1":{"frame":{"x":85,"y":112,"w":20,"h":34},"rotated":false,"trimmed":false,"spriteSourceSize":{"x":0,"y":0,"w":20,"h":34},"sourceSize":{"w":20,"h":34}},"Idle_2":{"frame":{"x":106,"y":112,"w":20,"h":34},"rotated":false,"trimmed":false,"spriteSourceSize":{"x":0,"y":0,"w":20,"h":34},"sourceSize":{"w":20,"h":34}},"Idle_3":{"frame":{"x":30,"y":112,"w":20,"h":34},"rotated":false,"trimmed":false,"spriteSourceSize":{"x":0,"y":0,"w":20,"h":34},"sourceSize":{"w":20,"h":34}},"Idle_4":{"frame":{"x":66,"y":77,"w":20,"h":34},"rotated":false,"trimmed":false,"spriteSourceSize":{"x":0,"y":0,"w":20,"h":34},"sourceSize":{"w":20,"h":34}},"Jump_1":{"frame":{"x":128,"y":35,"w":29,"h":34},"rotated":false,"trimmed":false,"spriteSourceSize":{"x":0,"y":0,"w":29,"h":34},"sourceSize":{"w":29,"h":34}},"Jump_2":{"frame":{"x":128,"y":0,"w":29,"h":34},"rotated":false,"trimmed":false,"spriteSourceSize":{"x":0,"y":0,"w":29,"h":34},"sourceSize":{"w":29,"h":34}},"Jump_3":{"frame":{"x":105,"y":182,"w":29,"h":34},"rotated":false,"trimmed":false,"spriteSourceSize":{"x":0,"y":0,"w":29,"h":34},"sourceSize":{"w":29,"h":34}},"Jump_4":{"frame":{"x":64,"y":0,"w":29,"h":34},"rotated":false,"trimmed":false,"spriteSourceSize":{"x":0,"y":0,"w":29,"h":34},"sourceSize":{"w":29,"h":34}},"Kick_1":{"frame":{"x":34,"y":77,"w":31,"h":34},"rotated":false,"trimmed":false,"spriteSourceSize":{"x":0,"y":0,"w":31,"h":34},"sourceSize":{"w":31,"h":34}},"Kick_2":{"frame":{"x":158,"y":140,"w":31,"h":34},"rotated":false,"trimmed":false,"spriteSourceSize":{"x":0,"y":0,"w":31,"h":34},"sourceSize":{"w":31,"h":34}},"Kick_3":{"frame":{"x":64,"y":147,"w":31,"h":34},"rotated":false,"trimmed":false,"spriteSourceSize":{"x":0,"y":0,"w":31,"h":34},"sourceSize":{"w":31,"h":34}},"Kick_4":{"frame":{"x":32,"y":147,"w":31,"h":34},"rotated":false,"trimmed":false,"spriteSourceSize":{"x":0,"y":0,"w":31,"h":34},"sourceSize":{"w":31,"h":34}},"Kick_5":{"frame":{"x":0,"y":147,"w":31,"h":34},"rotated":false,"trimmed":false,"spriteSourceSize":{"x":0,"y":0,"w":31,"h":34},"sourceSize":{"w":31,"h":34}},"Kick_6":{"frame":{"x":94,"y":35,"w":31,"h":34},"rotated":false,"trimmed":false,"spriteSourceSize":{"x":0,"y":0,"w":31,"h":34},"sourceSize":{"w":31,"h":34}},"Rifle_idle_1":{"frame":{"x":64,"y":35,"w":20,"h":34},"rotated":false,"trimmed":false,"spriteSourceSize":{"x":0,"y":0,"w":20,"h":34},"sourceSize":{"w":20,"h":34}},"Rifle_idle_2":{"frame":{"x":128,"y":105,"w":20,"h":34},"rotated":false,"trimmed":false,"spriteSourceSize":{"x":0,"y":0,"w":20,"h":34},"sourceSize":{"w":20,"h":34}},"Rifle_idle_3":{"frame":{"x":135,"y":182,"w":20,"h":34},"rotated":false,"trimmed":false,"spriteSourceSize":{"x":0,"y":0,"w":20,"h":34},"sourceSize":{"w":20,"h":34}},"Rifle_idle_4":{"frame":{"x":64,"y":182,"w":20,"h":34},"rotated":false,"trimmed":false,"spriteSourceSize":{"x":0,"y":0,"w":20,"h":34},"sourceSize":{"w":20,"h":34}},"Rifle_jump_1":{"frame":{"x":0,"y":0,"w":29,"h":34},"rotated":false,"trimmed":false,"spriteSourceSize":{"x":0,"y":0,"w":29,"h":34},"sourceSize":{"w":29,"h":34}},"Rifle_jump_2":{"frame":{"x":128,"y":70,"w":29,"h":34},"rotated":false,"trimmed":false,"spriteSourceSize":{"x":0,"y":0,"w":29,"h":34},"sourceSize":{"w":29,"h":34}},"Rifle_jump_3":{"frame":{"x":0,"y":182,"w":29,"h":34},"rotated":false,"trimmed":false,"spriteSourceSize":{"x":0,"y":0,"w":29,"h":34},"sourceSize":{"w":29,"h":34}},"Rifle_jump_4":{"frame":{"x":0,"y":112,"w":29,"h":34},"rotated":false,"trimmed":false,"spriteSourceSize":{"x":0,"y":0,"w":29,"h":34},"sourceSize":{"w":29,"h":34}},"Rifle_run_1":{"frame":{"x":94,"y":0,"w":33,"h":34},"rotated":false,"trimmed":false,"spriteSourceSize":{"x":0,"y":0,"w":33,"h":34},"sourceSize":{"w":33,"h":34}},"Rifle_run_2":{"frame":{"x":30,"y":182,"w":33,"h":34},"rotated":false,"trimmed":false,"spriteSourceSize":{"x":0,"y":0,"w":33,"h":34},"sourceSize":{"w":33,"h":34}},"Rifle_run_3":{"frame":{"x":94,"y":70,"w":33,"h":34},"rotated":false,"trimmed":false,"spriteSourceSize":{"x":0,"y":0,"w":33,"h":34},"sourceSize":{"w":33,"h":34}},"Rifle_run_4":{"frame":{"x":96,"y":147,"w":33,"h":34},"rotated":false,"trimmed":false,"spriteSourceSize":{"x":0,"y":0,"w":33,"h":34},"sourceSize":{"w":33,"h":34}},"Rifle_run_5":{"frame":{"x":156,"y":182,"w":33,"h":34},"rotated":false,"trimmed":false,"spriteSourceSize":{"x":0,"y":0,"w":33,"h":34},"sourceSize":{"w":33,"h":34}},"Rifle_run_6":{"frame":{"x":0,"y":77,"w":33,"h":34},"rotated":false,"trimmed":false,"spriteSourceSize":{"x":0,"y":0,"w":33,"h":34},"sourceSize":{"w":33,"h":34}},"Run_1":{"frame":{"x":30,"y":0,"w":33,"h":34},"rotated":false,"trimmed":false,"spriteSourceSize":{"x":0,"y":0,"w":33,"h":34},"sourceSize":{"w":33,"h":34}},"Run_2":{"frame":{"x":158,"y":70,"w":33,"h":34},"rotated":false,"trimmed":false,"spriteSourceSize":{"x":0,"y":0,"w":33,"h":34},"sourceSize":{"w":33,"h":34}},"Run_3":{"frame":{"x":158,"y":0,"w":33,"h":34},"rotated":false,"trimmed":false,"spriteSourceSize":{"x":0,"y":0,"w":33,"h":34},"sourceSize":{"w":33,"h":34}},"Run_4":{"frame":{"x":51,"y":112,"w":33,"h":34},"rotated":false,"trimmed":false,"spriteSourceSize":{"x":0,"y":0,"w":33,"h":34},"sourceSize":{"w":33,"h":34}},"Run_5":{"frame":{"x":158,"y":35,"w":33,"h":34},"rotated":false,"trimmed":false,"spriteSourceSize":{"x":0,"y":0,"w":33,"h":34},"sourceSize":{"w":33,"h":34}},"Run_6":{"frame":{"x":158,"y":105,"w":33,"h":34},"rotated":false,"trimmed":false,"spriteSourceSize":{"x":0,"y":0,"w":33,"h":34},"sourceSize":{"w":33,"h":34}},"Death_2":{"frame":{"x":0,"y":49,"w":25,"h":27},"rotated":false,"trimmed":false,"spriteSourceSize":{"x":0,"y":0,"w":25,"h":27},"sourceSize":{"w":25,"h":27}},"Death_3":{"frame":{"x":130,"y":147,"w":26,"h":20},"rotated":false,"trimmed":false,"spriteSourceSize":{"x":0,"y":0,"w":26,"h":20},"sourceSize":{"w":26,"h":20}},"Death_4":{"frame":{"x":26,"y":49,"w":31,"h":15},"rotated":false,"trimmed":false,"spriteSourceSize":{"x":0,"y":0,"w":31,"h":15},"sourceSize":{"w":31,"h":15}},"Death_5":{"frame":{"x":0,"y":35,"w":34,"h":13},"rotated":false,"trimmed":false,"spriteSourceSize":{"x":0,"y":0,"w":34,"h":13},"sourceSize":{"w":34,"h":13}},"Death_6":{"frame":{"x":26,"y":65,"w":36,"h":10},"rotated":false,"trimmed":false,"spriteSourceSize":{"x":0,"y":0,"w":36,"h":10},"sourceSize":{"w":36,"h":10}},"Death_1":{"frame":{"x":85,"y":182,"w":19,"h":34},"rotated":false,"trimmed":false,"spriteSourceSize":{"x":0,"y":0,"w":19,"h":34},"sourceSize":{"w":19,"h":34}}},"meta":{"app":"https://www.leshylabs.com/apps/sstool/","version":"Leshy SpriteSheet Tool v0.8.4","image":"Biker_new.png","size":{"w":191,"h":216},"scale":1}}